aspergil/__init__.py
aspergil/templates/hostname.template
aspergil/templates/hosts.template
aspergil/templates/interfaces.template
aspergil-1.0.0b12.dist-info/DESCRIPTION.rst
aspergil-1.0.0b12.dist-info/METADATA
aspergil-1.0.0b12.dist-info/RECORD
aspergil-1.0.0b12.dist-info/WHEEL
aspergil-1.0.0b12.dist-info/entry_points.txt
aspergil-1.0.0b12.dist-info/metadata.json
aspergil-1.0.0b12.dist-info/top_level.txt
