Metadata-Version: 2.0
Name: aspergil
Version: 1.0.0b12
Summary: Utlility script to set an Ubuntu machine's name and ip address
Home-page: https://github.com/fabiool/aspergil
Author: Fabio Oliveira
Author-email: me@fabiool.eu
License: Apache Software License Version 2.0
Keywords: virtual machines clones setup rename ip address hosts hostname interfaces
Platform: UNKNOWN
Classifier: Development Status :: 4 - Beta
Classifier: Environment :: Console
Classifier: Intended Audience :: Developers
Classifier: Intended Audience :: Information Technology
Classifier: Intended Audience :: System Administrators
Classifier: License :: OSI Approved :: Apache Software License
Classifier: Natural Language :: English
Classifier: Operating System :: POSIX :: Linux
Classifier: Programming Language :: Python
Classifier: Topic :: System :: Clustering
Classifier: Topic :: System :: Distributed Computing
Classifier: Topic :: System :: Installation/Setup
Classifier: Topic :: System :: Networking
Classifier: Topic :: System :: Systems Administration
Classifier: Topic :: Utilities
Requires-Dist: Jinja2 (>=2.8)
